Metadata-Version: 2.1
Name: pytrends-async
Version: 0.3.1
Summary: Pseudo API for Google Trends with asyncio support.
Home-page: https://github.com/KyleKreutzer/pytrends-async
Author: Kyle Kreutzer
Author-email: kyleakreutzer@gmail.com
License: Apache 2.0
Download-URL: https://github.com/KyleKreutzer/pytrends-async/archive/0.3.1.tar.gz
Keywords: google trends api search async asyncio
Platform: UNKNOWN
Classifier: Development Status :: 4 - Beta
Classifier: Intended Audience :: Developers
Classifier: Programming Language :: Python :: 3.6
Classifier: Programming Language :: Python :: 3.7
Classifier: Programming Language :: Python :: 3.8
Classifier: License :: OSI Approved :: MIT License
